utpd_oauth_client/__init__.py
utpd_oauth_client/client.py
utpd_oauth_client/exceptions.py
utpd_oauth_client/fastapi.py
utpd_oauth_client/nicegui.py
utpd_oauth_client/py.typed
utpd_oauth_client-0.2.0.dist-info/WHEEL
utpd_oauth_client-0.2.0.dist-info/METADATA
utpd_oauth_client-0.2.0.dist-info/RECORD
