Metadata-Version: 2.4
Name: utpd-oauth-client
Version: 0.2.0
Summary: Client library for utpd-oauth service with framework integrations
Author: Wardy
Author-email: Wardy <wardy3@gmail.com>
License-Expression: MIT
Classifier: Development Status :: 4 - Beta
Classifier: Framework :: FastAPI
Classifier: Intended Audience :: Developers
Classifier: License :: OSI Approved :: MIT License
Classifier: Operating System :: OS Independent
Classifier: Programming Language :: Python :: 3
Classifier: Programming Language :: Python :: 3.14
Classifier: Topic :: Internet :: WWW/HTTP
Classifier: Topic :: Software Development :: Libraries :: Python Modules
Classifier: Typing :: Typed
Requires-Dist: httpx>=0.28.1
Requires-Python: >=3.14
